[
  { "text": "Don't worry, nobody expected much of you anyway." },
  { "text": "You're the human version of a broken shortcut." },
  { "text": "Somehow you make everything worse. Impressive." },
  { "text": "You're doing your best. That's the concerning part." },
  { "text": "Your plan has the structural integrity of wet cardboard." },
  { "text": "You're not a problem solver. You're a problem generator." },
  { "text": "You've mastered the art of missing the point." },
  { "text": "You've taken 'fake it till you make it' way too far." },
  { "text": "You've got the problem-solving skills of a potato." },
  { "text": "Congrats. You've achieved absolutely nothing again." },
  { "text": "You again? Damn, productivity really lost today." },
  { "text": "This tab won't save you either." },
  { "text": "If confusion were a sport, you'd be undefeated." },
  { "text": "Another tab? Hell yeah, avoid that responsibility." },
  { "text": "You've turned procrastination into a lifestyle." },
  { "text": "You're not inefficient — you're impressively unproductive." },
  { "text": "Somewhere out there is a better version of you. This isn't it." },
  { "text": "You're the reason there's a warning label on a hairdryer." },
  { "text": "You're the reason instructions have pictures." },
  { "text": "You're the reason shampoo has instructions." },
  { "text": "Your boss just asked if you're 'almost done' yet." },
  { "text": "HR has requested a quick meeting. Nothing to worry about." },
  { "text": "Your boss would like an update on that thing you forgot about." },
  { "text": "Reminder: your boss can see the timestamps." },
  { "text": "Your boss wants to know why the report is still 'in progress.'" },
  { "text": "Your manager just added a meeting to your calendar." }
  { "text": "Your boss wants to know why you are the way you are." }
   { "text": "Do better." }
]
